mastercard_remittance-1.0.4.dist-info/DESCRIPTION.rst
mastercard_remittance-1.0.4.dist-info/METADATA
mastercard_remittance-1.0.4.dist-info/RECORD
mastercard_remittance-1.0.4.dist-info/WHEEL
mastercard_remittance-1.0.4.dist-info/metadata.json
mastercard_remittance-1.0.4.dist-info/top_level.txt
mastercardremittance/__init__.py
mastercardremittance/cancelremittance.py
mastercardremittance/quotes.py
mastercardremittance/remittancefundingandpayment.py
mastercardremittance/remittancepayment.py
mastercardremittance/resourceconfig.py
mastercardremittance/retrieveremittance.py
mastercardremittance/sanctionscreening.py
